{"note":"Don't delete this file! It's used internally to help with page regeneration.","google":"UA-22488443-16","tagline":"\"an easy-on-the-eyes Sublime Text/TextMate color scheme.","name":"Ciapre","body":"## Ciapre ##\r\nCiapre - an easy on the eyes Sublime Text/TextMate color scheme.\r\n* Updated: Now included in Sublime Package Control. Install it! ♥ (^o^)/\r\n\r\n##### *Learn more*\r\n+ [Github page](http://vinhnx.github.com/Ciapre.tmTheme/)\r\n+ [Introduction post on my blog](http://vinhnx.github.com/blog/2012/09/21/ciapre-sublime-text-color-scheme/)\r\n\r\n## Comes with two different colors ##\r\n##### Darken black\r\n![Ciapre Black](https://dl.dropbox.com/u/11357190/Shared%20Images/ciapre-new.PNG)\r\n\r\n![Ciapre Black](https://dl.dropbox.com/u/11357190/Shared%20Images/awesome%20ciapre%20black%20-%20sd.png)\r\n\r\n##### Blue\r\n![Ciapre](https://dl.dropbox.com/u/11357190/Shared%20Images/Ciapre%20ST%20theme%20preview%205%20-sd.PNG)\r\n\r\n## How to install & use ##\r\n### Via Package Control:\r\nOpen Package Control and search for `Ciapre`, install it.\r\n\r\nNow in your beloved Sublime Text, open Preferences -> Color Scheme -> Ciapre > now you can choose either [Ciapre] or [Ciapre Black].\r\n\r\nEnjoy! :)\r\n\r\n### The Manual way:\r\nCopy your desired tmTheme and paste it in Package folder.\r\n\r\nOn Windows, it is located in C:\\Users\\YOUR-NAME\\AppData\\Roaming\\Sublime Text 2\\Packages\r\n\r\nEnter `User` folder, and paste it in.\r\n\r\nIn your opened Sublime Text, browse to Preferences -> Color Scheme -> User -> Ciapre\r\n\r\nOr you can clone this in you Packages folder\r\n\r\n`git clone https://github.com/vinhnx/Ciapre.tmTheme.git`\r\n\r\n.. then activate via Preferences -> Color Scheme -> Ciapre.tmTheme\r\n\r\n### *Tips* ###\r\nUse great with [Aqua](https://github.com/cafarm/aqua-theme) theme - Prokit. \r\nYou won't be disappointed!\r\n\r\n~ Happy coding ♥"}